supportr/__init__.py
supportr/convert_examples_to_features.py
supportr/download_features.py
supportr/predict.py
supportr/regression_processor.py
supportr/supportr.py
supportr-1.2.dist-info/METADATA
supportr-1.2.dist-info/WHEEL
supportr-1.2.dist-info/top_level.txt
supportr-1.2.dist-info/RECORD
