Metadata-Version: 2.1
Name: supportr
Version: 1.2
Summary: supportr
Home-page: UNKNOWN
Author: Junjie Wu
Author-email: wujj38@mail2.sysu.edu.cn
License: UNKNOWN
Platform: UNKNOWN
Requires-Python: >=3.6
